dephell_pythons-0.1.15.dist-info/dependency_links.txt
dephell_pythons-0.1.15.dist-info/entry_points.txt
dephell_pythons-0.1.15.dist-info/METADATA
dephell_pythons-0.1.15.dist-info/top_level.txt
dephell_pythons-0.1.15.dist-info/WHEEL
dephell_pythons/_shell_utils.py
dephell_pythons/_cached_property.py
dephell_pythons/_python.py
dephell_pythons/_constants.py
dephell_pythons/__init__.py
dephell_pythons/_pythons.py
dephell_pythons/__main__.py
dephell_pythons/_finder.py
dephell_pythons/_windows.py
dephell_pythons/pep514tools/environment.py
dephell_pythons/pep514tools/__init__.py
dephell_pythons/pep514tools/_registry.py
dephell_pythons/pep514tools/__main__.py
dephell_pythons-0.1.15.dist-info/LICENSE
dephell_pythons-0.1.15.dist-info/RECORD