Metadata-Version: 2.1
Name: dephell-pythons
Version: 0.1.15
Summary: Work with python versions
Project-URL: Repository, https://github.com/dephell/dephell_pythons
Author: Gram
Author-email: mail@orsinium.dev
License: MIT
Requires-Python: >=3.6
Keywords: dephell,python,pythons,interpreter,pyenv,asdf,pip,pipenv
Classifier: Development Status :: 4 - Beta
Classifier: Environment :: Console
Classifier: Intended Audience :: Developers
Classifier: License :: OSI Approved :: MIT License
Classifier: Programming Language :: Python
Classifier: Topic :: Software Development :: Libraries :: Python Modules
Requires-Dist: attrs
Requires-Dist: dephell-specifier
Requires-Dist: packaging
